{
  "SourceRepoUri": "https://ceapex.visualstudio.com/CEINTL/_git/mvp-site",
  "SourceRepoLocale": "en-US",
  "Branch": "develop",
  "Locales": null,
  "Owner": "MicrosoftDocs",
  "TargetRepoUris": null,
  "RenamePatternKey": "[filename].[language].[extension]",
  "TargetRepoBranch": "develop",
  "TargetRepoBilingualBranch": "develop-sxs",
  "ProjectName": null,
  "Permission": {
    "Admin": [
      "CEIC_Admin",
      "OpenLocalization"
    ],
    "Write": [
      "CEIC",
      "MOR"
    ],
    "Read": [
      "Everyone"
    ]
  },
  "HandoffRepoUri": null,
  "HandbackRepoUri": null,
  "EmptyBranches": [
    "master",
    "master-sxs",
    "live",
    "live-sxs"
  ],
  "NoHandoffOnPublishError": false,
  "InsertMetadataHeaderIfNotExists": false,
  "IncrementalLocSyncing": false,
  "AllBranches": [
    "develop",
    "develop-sxs",
    "master",
    "master-sxs",
    "live",
    "live-sxs"
  ],
  "Tenant": "C&E",
  "HostContentStore": "mvp-site_develop",
  "PublishPlatform": "Unknown",
  "RepoIds": null,
  "TargetRepoPublishBranch": null,
  "PathFilter": [
    "**/*"
  ],
  "TranslatorType": 1,
  "IntervalSeconds": 10800,
  "MetadataMappings": {
    "Host File Tags": [
      "ms.topic",
      "ms.search.region",
      "ms.search.industry",
      "audience",
      "ms.service"
    ],
    "Host File Priority": [
      "localization_priority",
      "localizationpriority",
      "ms.localizationpriority"
    ],
    "Host File Title": [
      "title"
    ]
  },
  "FilesToCopy": null,
  "AllFilesAsLead": true,
  "Priority": 0,
  "DisableLocRepoSyncing": false,
  "BundleHandoff": false,
  "TranslationOptions": {
    "exposeImageTitleText": "True",
    "exposeLinkTitleText": "True",
    "exposePageTitle": "True",
    "linkifyHeaders": "True",
    "lockAtSign": "True",
    "lockBackslashEscapeChars": "True",
    "mergeAdjacentPhTags": "False",
    "pairHtmlTags": "True",
    "preset": "cne",
    "replaceNewlineWithWhitespace": "True",
    "trimBoundingPhTags": "False",
    "useParagraphMarker": "False",
    "YmlFormat": "yml-origin"
  },
  "MrefOptions": null,
  "XliffVersion": "1.2",
  "TrainXliff": false,
  "SkipXliffTransform": true,
  "FileExtensionsEnableXliffTransform": null,
  "Id": "https://ceapex.visualstudio.com/CEINTL/_git/mvp-site:develop",
  "TranslationLocales": [
    "en-US"
  ],
  "NoLocales": true
}