{
  "SourceRepoUri": "https://github.com/xamarin/documentation",
  "SourceRepoLocale": "en-US",
  "Branch": "master",
  "Locales": [
    "pt-BR",
    "zh-CN",
    "de-DE",
    "ja-JP",
    "es-ES"
  ],
  "Owner": "Xamarin",
  "TargetRepoUris": {
    "pt-BR": "https://github.com/xamarin/documentation.pt-br",
    "zh-CN": "https://github.com/xamarin/documentation.zh-cn",
    "de-DE": "https://github.com/xamarin/documentation.de-de",
    "ja-JP": "https://github.com/xamarin/documentation.ja-jp",
    "es-ES": "https://github.com/xamarin/documentation.es-es"
  },
  "RenamePatternKey": null,
  "TargetRepoBranch": "master",
  "TargetRepoBilingualBranch": "master-sxs",
  "ProjectName": null,
  "Permission": {
    "Admin": [
      "SonjaSalzman",
      "OpenLocalization",
      "OpenLocalization"
    ]
  },
  "HandoffRepoUri": null,
  "HandbackRepoUri": null,
  "EmptyBranches": [
    "master",
    "master-sxs",
    "live",
    "live-sxs"
  ],
  "NoHandoffOnPublishError": false,
  "InsertMetadataHeaderIfNotExists": false,
  "IncrementalLocSyncing": false,
  "AllBranches": [
    "master",
    "master-sxs",
    "live",
    "live-sxs"
  ],
  "Tenant": "C&E",
  "HostContentStore": "Xamarin_Doc",
  "PublishPlatform": "General",
  "RepoIds": {},
  "TargetRepoPublishBranch": "master-sxs",
  "PathFilter": [
    "**/*"
  ],
  "TranslatorType": 0,
  "IntervalSeconds": 10800,
  "MetadataMappings": {
    "Host File Tags": [
      "ms.topic",
      "ms.search.region",
      "ms.search.industry",
      "audience",
      "ms.service"
    ],
    "Host File Title": [
      "title"
    ],
    "Host File Priority": [
      "localization_priority",
      "localizationpriority",
      "ms.localizationpriority"
    ]
  },
  "FilesToCopy": [
    "**\\.openpublishing.redirection.json"
  ],
  "AllFilesAsLead": false,
  "Priority": 0,
  "DisableLocRepoSyncing": false,
  "BundleHandoff": false,
  "TranslationOptions": {
    "exposeImageTitleText": "True",
    "exposeLinkTitleText": "True",
    "exposePageTitle": "True",
    "linkifyHeaders": "True",
    "lockAtSign": "True",
    "lockBackslashEscapeChars": "True",
    "mergeAdjacentPhTags": "False",
    "pairHtmlTags": "True",
    "preset": "cne",
    "replaceNewlineWithWhitespace": "True",
    "trimBoundingPhTags": "False",
    "useParagraphMarker": "False",
    "YmlFormat": "yml-origin"
  },
  "MrefOptions": null,
  "XliffVersion": "1.2",
  "TrainXliff": false,
  "SkipXliffTransform": null,
  "FileExtensionsEnableXliffTransform": null,
  "Id": "https://github.com/xamarin/documentation:master",
  "TranslationLocales": [
    "pt-BR",
    "zh-CN",
    "de-DE",
    "ja-JP",
    "es-ES"
  ],
  "NoLocales": false
}